pbi_pyadomd/Microsoft.AnalysisServices.AdomdClient.dll
pbi_pyadomd/__init__.py
pbi_pyadomd/__init__.pyi
pbi_pyadomd/c_sharp_type_mapping.py
pbi_pyadomd/conn.py
pbi_pyadomd/reader.py
pbi_pyadomd/utils.py
pbi_pyadomd/xml_error_handling.py
pbi_pyadomd/Microsoft/__init__.py
pbi_pyadomd/Microsoft/AnalysisServices/AdomdClient.pyi
pbi_pyadomd/Microsoft/AnalysisServices/__init__.py
pbi_pyadomd/Microsoft/AnalysisServices/enums.py
pbi_pyadomd-1.4.3.dist-info/METADATA
pbi_pyadomd-1.4.3.dist-info/WHEEL
pbi_pyadomd-1.4.3.dist-info/licenses/LICENSE
pbi_pyadomd-1.4.3.dist-info/RECORD
