Metadata-Version: 2.4
Name: pbi_pyadomd
Version: 1.4.3
Summary: A fork of pyadomd, providing a typed python interface for communicating with an SSAS instance
Project-URL: Homepage, https://github.com/douglassimonsen/pbi_pyadomd
Project-URL: Documentation, https://douglassimonsen.github.io/pbi_pyadomd/
License-File: LICENSE
Requires-Python: >=3.11.0
Requires-Dist: beautifulsoup4>=4.12.3
Requires-Dist: pythonnet>=3.0.0
Requires-Dist: pythonnet>=3.0.3
Requires-Dist: structlog>=25.4.0
Provides-Extra: dev
Requires-Dist: build>=1.2.2; extra == 'dev'
Requires-Dist: pre-commit>=3.8.0; extra == 'dev'
Requires-Dist: ruff>=0.12.7; extra == 'dev'
Provides-Extra: docs
Requires-Dist: mkdocs-material>=9.6.16; extra == 'docs'
Requires-Dist: mkdocs>=1.6.1; extra == 'docs'
Requires-Dist: mkdocstrings-python>=0.30.0; extra == 'docs'
